barchart/__init__.py
barchart/version.py
barchart_ondemand_client_python-0.0.6.dist-info/DESCRIPTION.rst
barchart_ondemand_client_python-0.0.6.dist-info/METADATA
barchart_ondemand_client_python-0.0.6.dist-info/RECORD
barchart_ondemand_client_python-0.0.6.dist-info/WHEEL
barchart_ondemand_client_python-0.0.6.dist-info/metadata.json
barchart_ondemand_client_python-0.0.6.dist-info/top_level.txt
