Metadata-Version: 2.0
Name: barchart-ondemand-client-python
Version: 0.0.6
Summary: A Python library to get data from BarChartOnDemand API
Home-page: https://github.com/lanshark/barchart-ondemand-client-python
Author: Scott Sharkey
Author-email: ssharkey@lanshark.com
License: MIT
Keywords: BarChartOnDemand python trading data client interface
Platform: UNKNOWN
Classifier: Development Status :: 4 - Beta
Classifier: Environment :: Console
Classifier: Intended Audience :: Developers
Classifier: Operating System :: OS Independent
Classifier: Programming Language :: Cython
Classifier: Programming Language :: Python
Classifier: Programming Language :: Python :: 2
Classifier: Programming Language :: Python :: 2.7
Classifier: Programming Language :: Python :: 3
Classifier: Programming Language :: Python :: 3.4
Classifier: Programming Language :: Python :: 3.5
Classifier: Programming Language :: Python :: 3.6
Classifier: License :: OSI Approved :: MIT License
Requires-Dist: python-dateutil
Requires-Dist: requests
Requires-Dist: requests-cache
Requires-Dist: six
Provides-Extra: dev
Requires-Dist: check-manifest; extra == 'dev'
Requires-Dist: pytest; extra == 'dev'
Provides-Extra: test
Requires-Dist: coverage; extra == 'test'
Requires-Dist: pytest; extra == 'test'
